LICENSE.txt
MANIFEST.in
README.md
setup.py
lintswitch/__init__.py
lintswitch/checkers.py
lintswitch/emitters.py
lintswitch/http_server.py
lintswitch/index.html
lintswitch/main.py
lintswitch.egg-info/PKG-INFO
lintswitch.egg-info/SOURCES.txt
lintswitch.egg-info/dependency_links.txt
lintswitch.egg-info/entry_points.txt
lintswitch.egg-info/requires.txt
lintswitch.egg-info/top_level.txt