Metadata-Version: 1.0
Name: lintswitch
Version: 2.3.4
Summary: Lint your Python in real-time
Home-page: https://github.com/grahamking/lintswitch
Author: Graham King
Author-email: graham@gkgk.org
License: UNKNOWN
Platform: UNKNOWN
Classifier: Development Status :: 4 - Beta
Classifier: Environment :: Console
Classifier: Intended Audience :: Developers
Classifier: License :: OSI Approved :: GNU General Public License (GPL)
Classifier: Operating System :: OS Independent
Classifier: Programming Language :: Python
Classifier: Topic :: Software Development :: Quality Assurance
